gcs_vectors/__init__.py
gcs_vectors/client.py
gcs_vectors/core/__init__.py
gcs_vectors/core/cache.py
gcs_vectors/core/index.py
gcs_vectors/core/query.py
gcs_vectors/core/storage.py
gcs_vectors/utils/__init__.py
gcs_vectors/utils/helpers.py
gcs_vectors/utils/logger.py
gcs_vectors-0.0.1.dist-info/licenses/LICENSE
gcs_vectors-0.0.1.dist-info/METADATA
gcs_vectors-0.0.1.dist-info/WHEEL
gcs_vectors-0.0.1.dist-info/top_level.txt
gcs_vectors-0.0.1.dist-info/RECORD
