Metadata-Version: 2.4
Name: gcs-vectors
Version: 0.0.1
Summary: A lightweight vector search library that uses GCS with HNS as the storage engine.
Author-email: "xCommand.ai" <engineer@xcommand.ai>
License:                                  Apache License
Project-URL: Homepage, https://github.com/xcommand-ai/gcs-vectors
Project-URL: Repository, https://github.com/xcommand-ai/gcs-vectors
Project-URL: Issues, https://github.com/xcommand-ai/gcs-vectors/issues
Classifier: Development Status :: 4 - Beta
Classifier: Intended Audience :: Developers
Classifier: License :: OSI Approved :: Apache Software License
Classifier: Programming Language :: Python :: 3
Classifier: Programming Language :: Python :: 3.10
Classifier: Programming Language :: Python :: 3.11
Classifier: Topic :: Scientific/Engineering :: Artificial Intelligence
Classifier: Topic :: Database
Requires-Python: >=3.10
License-File: LICENSE
Requires-Dist: gcsfs>=2024.1.0
Requires-Dist: pyarrow>=14.0.0
Requires-Dist: numpy>=1.24.0
Requires-Dist: scipy>=1.10.0
Requires-Dist: pandas>=2.0.0
Provides-Extra: dev
Requires-Dist: pytest>=7.0.0; extra == "dev"
Requires-Dist: pytest-asyncio>=0.21.0; extra == "dev"
Requires-Dist: faiss-cpu>=1.7.4; extra == "dev"
Requires-Dist: build; extra == "dev"
Requires-Dist: twine; extra == "dev"
Dynamic: license-file
